HISTORY.txt
MANIFEST.in
README.txt
refresh.txt
setup.py
version.txt
Products/__init__.py
Products.FAQulator.egg-info/PKG-INFO
Products.FAQulator.egg-info/SOURCES.txt
Products.FAQulator.egg-info/dependency_links.txt
Products.FAQulator.egg-info/entry_points.txt
Products.FAQulator.egg-info/namespace_packages.txt
Products.FAQulator.egg-info/not-zip-safe
Products.FAQulator.egg-info/top_level.txt
Products/FAQulator/FAQ.py
Products/FAQulator/FAQEntry.py
Products/FAQulator/__init__.py
Products/FAQulator/config.py
Products/FAQulator/Extensions/Install.py
Products/FAQulator/Extensions/__init__.py
Products/FAQulator/i18n/faq-cs.po
Products/FAQulator/i18n/faq-el.po
Products/FAQulator/i18n/faq-es.po
Products/FAQulator/i18n/faq-fr.po
Products/FAQulator/i18n/faq-nl.po
Products/FAQulator/i18n/faq-no.po
Products/FAQulator/i18n/faq-pl.po
Products/FAQulator/i18n/faq-plone-pt-br.po
Products/FAQulator/i18n/faq-pt-br.po
Products/FAQulator/i18n/faq.pot
Products/FAQulator/i18n/usei18ndude.sh
Products/FAQulator/profiles/default/propertiestool.xml
Products/FAQulator/profiles/default/skins.xml
Products/FAQulator/profiles/default/types.xml
Products/FAQulator/profiles/default/types/FAQ.xml
Products/FAQulator/profiles/default/types/FAQEntry.xml
Products/FAQulator/skins/faqulator/faq_icon.gif
Products/FAQulator/skins/faqulator/faq_view.pt
Products/FAQulator/skins/faqulator/faqentry_view.pt