Metadata-Version: 1.0
Name: Products.FAQulator
Version: 1.6
Summary: This product implements a simple FAQ content type.
Home-page: https://github.com/zestsoftware/Products.FAQulator
Author: UNKNOWN
Author-email: UNKNOWN
License: GPL
Platform: UNKNOWN
Classifier: Framework :: Plone
Classifier: Framework :: Plone :: 4.2
Classifier: Framework :: Plone :: 4.3
Classifier: Programming Language :: Python
